COPYING.rst
MANIFEST.in
Makefile
README.rst
setup.py
distarray/__init__.py
distarray/__version__.py
distarray/error.py
distarray/metadata_utils.py
distarray/mpi_engine.py
distarray/mpionly_utils.py
distarray/run_tests.py
distarray/testing.py
distarray/utils.py
distarray.egg-info/PKG-INFO
distarray.egg-info/SOURCES.txt
distarray.egg-info/dependency_links.txt
distarray.egg-info/entry_points.txt
distarray.egg-info/pbr.json
distarray.egg-info/requires.txt
distarray.egg-info/top_level.txt
distarray/apps/__init__.py
distarray/apps/dacluster.py
distarray/apps/engine.py
distarray/externals/__init__.py
distarray/externals/protocol_validator.py
distarray/externals/six.py
distarray/globalapi/__init__.py
distarray/globalapi/context.py
distarray/globalapi/distarray.py
distarray/globalapi/functions.py
distarray/globalapi/ipython_cleanup.py
distarray/globalapi/ipython_utils.py
distarray/globalapi/maps.py
distarray/globalapi/random.py
distarray/globalapi/tests/__init__.py
distarray/globalapi/tests/launch_mpi.py
distarray/globalapi/tests/test_context.py
distarray/globalapi/tests/test_distarray.py
distarray/globalapi/tests/test_distributed_io.py
distarray/globalapi/tests/test_functions.py
distarray/globalapi/tests/test_maps.py
distarray/globalapi/tests/test_random.py
distarray/localapi/__init__.py
distarray/localapi/construct.py
distarray/localapi/error.py
distarray/localapi/format.py
distarray/localapi/localarray.py
distarray/localapi/maps.py
distarray/localapi/mpiutils.py
distarray/localapi/proxyize.py
distarray/localapi/random.py
distarray/localapi/tests/__init__.py
distarray/localapi/tests/paralleltest_distributed_array_protocol.py
distarray/localapi/tests/paralleltest_functions.py
distarray/localapi/tests/paralleltest_io.py
distarray/localapi/tests/paralleltest_localarray.py
distarray/localapi/tests/paralleltest_maps.py
distarray/localapi/tests/paralleltest_mpiutils.py
distarray/localapi/tests/paralleltest_random.py
distarray/localapi/tests/paralleltest_umath.py
distarray/localapi/tests/test_format.py
distarray/localapi/tests/test_maps.py
distarray/localapi/tests/test_mpiutils.py
distarray/plotting/__init__.py
distarray/plotting/plotting.py
distarray/tests/__init__.py
