Metadata-Version: 1.1
Name: distarray
Version: 0.6.0
Summary: Distributed Memory Arrays for Python
Home-page: https://github.com/enthought/distarray
Author: DistArray Developers
Author-email: distarray@googlegroups.com
License: New BSD
Keywords: parallel mpi distributed array
Platform: Linux
Platform: Mac OS-X
Classifier: Development Status :: 3 - Alpha
Classifier: Intended Audience :: Developers
Classifier: Intended Audience :: Science/Research
Classifier: License :: OSI Approved :: BSD License
Classifier: Operating System :: MacOS
Classifier: Operating System :: OS Independent
Classifier: Operating System :: POSIX
Classifier: Operating System :: Unix
Classifier: Programming Language :: Python
Classifier: Topic :: Scientific/Engineering
Classifier: Topic :: Software Development
Classifier: Topic :: Software Development :: Libraries
